nadamq/command_proxy.py
nadamq/NadaMq.cpp
nadamq/NadaMq.pyd
nadamq/NadaMq.pyx
nadamq/__init__.py
nadamq/lib/NadaMQ-Arduino.tar.gz
nadamq/src/BufferAllocator.h
nadamq/src/crc-16.c
nadamq/src/crc-16.h
nadamq/src/crc_common.cpp
nadamq/src/crc_common.h
nadamq/src/Deque.h
nadamq/src/NadaMQ.h
nadamq/src/Packet.h
nadamq/src/PacketAllocator.h
nadamq/src/PacketHandler.h
nadamq/src/PacketParser.h
nadamq/src/PacketSocket.h
nadamq/src/PacketSocketEvents.h
nadamq/src/PacketStream.h
nadamq/src/PacketWriter.h
nadamq/src/packet_actions.cpp
nadamq/src/SimpleCommand.h
nadamq/src/StreamPacketParser.h
nadamq/src/Arduino/packet_handler/NadaMQ.h
nadamq/src/Arduino/packet_handler/output_buffer.h
nadamq/src/Arduino/packet_handler/packet_handler.h
nadamq/src/Arduino/packet_handler/simple.pb.c
nadamq/src/Arduino/packet_handler/simple.pb.h
nadamq/src/protobuf/nano/pb.h
nadamq/src/protobuf/nano/pb_decode.c
nadamq/src/protobuf/nano/pb_decode.h
nadamq/src/protobuf/nano/pb_encode.c
nadamq/src/protobuf/nano/pb_encode.h
nadamq-0.8.post1.dist-info/DESCRIPTION.rst
nadamq-0.8.post1.dist-info/METADATA
nadamq-0.8.post1.dist-info/metadata.json
nadamq-0.8.post1.dist-info/pbr.json
nadamq-0.8.post1.dist-info/RECORD
nadamq-0.8.post1.dist-info/top_level.txt
nadamq-0.8.post1.dist-info/WHEEL
