Metadata-Version: 2.0
Name: nadamq
Version: 0.8.post1
Summary: Embedded-friendly transport layer, inspired by ZeroMQ
Home-page: https://github.com/cfobel/nadamq
Author: Christian Fobel
Author-email: christian@fobel.net
License: GPL
Keywords: cython embedded zeromq transport packet parse
Platform: UNKNOWN
Requires-Dist: c-array-defs (>=0.1.post2)
